pypals/Emotions.py
pypals/Program.py
pypals/PyPal.py
pypals/__init__.py
pypals/__main__.py
pypals/_meta.py
pypals-1.0.4.dist-info/LICENSE.txt
pypals-1.0.4.dist-info/METADATA
pypals-1.0.4.dist-info/WHEEL
pypals-1.0.4.dist-info/top_level.txt
pypals-1.0.4.dist-info/RECORD
