Metadata-Version: 2.1
Name: pypals
Version: 1.0.4
Summary: Terminal buddies to store and run python snippets
Home-page: https://github.com/byteface/pypals
Author: @byteface
Author-email: byteface@gmail.com
License: MIT
Download-URL: https://github.com/byteface/pypals/archive/1.0.4.tar.gz
Keywords: pypals
Platform: UNKNOWN
Classifier: Intended Audience :: Developers
Classifier: Topic :: Software Development :: Build Tools
Classifier: Programming Language :: Python :: 3
Classifier: Programming Language :: Python :: 3.7
Classifier: License :: OSI Approved :: MIT License
Requires-Python: >=3.7
Requires-Dist: rich
Requires-Dist: domonic
